pyautd3_link_remote_twincat/__init__.py
pyautd3_link_remote_twincat/py.typed
pyautd3_link_remote_twincat/remote_twincat.py
pyautd3_link_remote_twincat/bin/autd3_capi_link_remote_twincat.dll
pyautd3_link_remote_twincat/native_methods/__init__.py
pyautd3_link_remote_twincat/native_methods/autd3_capi_link_remote_twincat.py
pyautd3_link_remote_twincat-37.0.0a3.dist-info/licenses/LICENSE
pyautd3_link_remote_twincat-37.0.0a3.dist-info/licenses/ThirdPartyNotices.txt
pyautd3_link_remote_twincat-37.0.0a3.dist-info/METADATA
pyautd3_link_remote_twincat-37.0.0a3.dist-info/WHEEL
pyautd3_link_remote_twincat-37.0.0a3.dist-info/top_level.txt
pyautd3_link_remote_twincat-37.0.0a3.dist-info/RECORD
