Metadata-Version: 2.4
Name: pyautd3_link_remote_twincat
Version: 37.0.0a3
Summary: autd3-link-remote-twincat library wrapper for python
Author-email: Shun Suzuki <suzuki@hapis.k.u-tokyo.ac.jp>
Project-URL: Repository, https://github.com/shinolab/pyautd3_link_remote_twincat.git
Classifier: Programming Language :: Python :: 3.12
Classifier: Programming Language :: Python :: 3.13
Classifier: Programming Language :: Python :: 3.14
Classifier: Operating System :: Microsoft :: Windows
Classifier: Operating System :: MacOS :: MacOS X
Classifier: Operating System :: POSIX
Requires-Python: >=3.12
License-File: LICENSE
License-File: ThirdPartyNotices.txt
Requires-Dist: numpy>=2
Requires-Dist: pyautd3==37.0.0a3
Dynamic: license-file
